odoo8_addon_mrp_calendar_view-8.0.1.0.0.99.dev15-py2.7-nspkg.pth
odoo8_addon_mrp_calendar_view-8.0.1.0.0.99.dev15.dist-info/METADATA
odoo8_addon_mrp_calendar_view-8.0.1.0.0.99.dev15.dist-info/RECORD
odoo8_addon_mrp_calendar_view-8.0.1.0.0.99.dev15.dist-info/WHEEL
odoo8_addon_mrp_calendar_view-8.0.1.0.0.99.dev15.dist-info/namespace_packages.txt
odoo8_addon_mrp_calendar_view-8.0.1.0.0.99.dev15.dist-info/top_level.txt
odoo_addons/mrp_calendar_view/README.rst
odoo_addons/mrp_calendar_view/__init__.py
odoo_addons/mrp_calendar_view/__openerp__.py
odoo_addons/mrp_calendar_view/i18n/ar.po
odoo_addons/mrp_calendar_view/i18n/bs.po
odoo_addons/mrp_calendar_view/i18n/ca.po
odoo_addons/mrp_calendar_view/i18n/cs.po
odoo_addons/mrp_calendar_view/i18n/de.po
odoo_addons/mrp_calendar_view/i18n/en_GB.po
odoo_addons/mrp_calendar_view/i18n/es.po
odoo_addons/mrp_calendar_view/i18n/es_CR.po
odoo_addons/mrp_calendar_view/i18n/es_EC.po
odoo_addons/mrp_calendar_view/i18n/es_MX.po
odoo_addons/mrp_calendar_view/i18n/es_VE.po
odoo_addons/mrp_calendar_view/i18n/et.po
odoo_addons/mrp_calendar_view/i18n/fi.po
odoo_addons/mrp_calendar_view/i18n/fr.po
odoo_addons/mrp_calendar_view/i18n/gl.po
odoo_addons/mrp_calendar_view/i18n/hr.po
odoo_addons/mrp_calendar_view/i18n/hu.po
odoo_addons/mrp_calendar_view/i18n/id.po
odoo_addons/mrp_calendar_view/i18n/it.po
odoo_addons/mrp_calendar_view/i18n/ja.po
odoo_addons/mrp_calendar_view/i18n/lt.po
odoo_addons/mrp_calendar_view/i18n/lv.po
odoo_addons/mrp_calendar_view/i18n/mk.po
odoo_addons/mrp_calendar_view/i18n/mn.po
odoo_addons/mrp_calendar_view/i18n/mrp_calendar_view.pot
odoo_addons/mrp_calendar_view/i18n/nb.po
odoo_addons/mrp_calendar_view/i18n/nl.po
odoo_addons/mrp_calendar_view/i18n/nl_BE.po
odoo_addons/mrp_calendar_view/i18n/pl.po
odoo_addons/mrp_calendar_view/i18n/pt.po
odoo_addons/mrp_calendar_view/i18n/pt_BR.po
odoo_addons/mrp_calendar_view/i18n/pt_PT.po
odoo_addons/mrp_calendar_view/i18n/ro.po
odoo_addons/mrp_calendar_view/i18n/ru.po
odoo_addons/mrp_calendar_view/i18n/sl.po
odoo_addons/mrp_calendar_view/i18n/sr@latin.po
odoo_addons/mrp_calendar_view/i18n/sv.po
odoo_addons/mrp_calendar_view/i18n/th.po
odoo_addons/mrp_calendar_view/i18n/tr.po
odoo_addons/mrp_calendar_view/i18n/tr_TR.po
odoo_addons/mrp_calendar_view/i18n/vi.po
